{
  "implemented": true,
  "name": "dewotttempestarii",
  "nationalPokedexNumber": 5001,
  "primaryType": "water",
  "secondaryType": "fighting",
  "abilities": [
    "ironfist",
    "scrappy",
    "h:intimidate"
  ],
   "baseScale": 0.7,
 "hitbox": {
   "width": 0.7,
   "height": 0.7,
   "fixed": false
 },
  "drops": {
    "amount": 2,
    "entries": [
      {
        "item": "minecraft:iron_ingot",
        "quantityRange": "10-15"
      },
      {
        "item": "cobblemon:starf_berry",
        "percentage": 10
      }
    ]
  },
  "baseStats": {
    "hp": 80,
    "attack":112,
    "defence": 60,
    "special_attack": 50,
    "special_defence": 60,
    "speed": 136
  },
  "catchRate": 10,
  "maleRatio": 1,
  "shoulderMountable": false,
  "baseExperienceYield": 169,
  "experienceGroup": "slow",
  "eggCycles": 20,
  "eggGroups": [
    "undiscovered"
  ],
  "moves": [
    "1:wickedblow",
    "1:bulletpunch",
    "1:suckerpunch",
    "1:machpunch",
    "1:surgingstrikes",
    "13:poweruppunch",
    "18:razorshell",
    "21:furycutter",
    "23:lowkick",
    "26:waterpulse",
    "27:bulkup",
    "29:aerialace",
    "34:aquajet",
    "37:encore",
    "42:aquatail",
    "45:retaliate",
    "50:fakeout",
    "53:hydropump",
    "54:followme",
    "54:taunt",
    "57:obstruct",
    "59:extremespeed",
    "62:upperhand",
    "67:focuspunch",
    "70:thunderpunch",
    "70:icepunch",
    "70:firepunch",
    "70:jetpunch",
    "70:bulletpunch",
    "75:plasmafists",
    "78:axekick",
    "78:highjumpkick",
    "80:closecombat",
    "82:skullbash",
    "85:quickguard",
    "87:flipturn",
    "90:tripleaxel",
    "95:foulplay",
    "egg:airslash",
    "egg:aquacutter",
    "egg:copycat",
    "egg:detect",
    "egg:knockoff",
    "egg:nightslash",
    "egg:sacredsword",
    "egg:screech",
    "egg:trumpcard",
    "tm:aerialace",
    "tm:airslash",
    "tm:aquatail",
    "tm:assurance",
    "tm:avalanche",
    "tm:blizzard",
    "tm:brickbreak",
    "tm:brine",
    "tm:chillingwater",
    "tm:covet",
    "tm:cut",
    "tm:dig",
    "tm:dive",
    "tm:encore",
    "tm:endure",
    "tm:facade",
    "tm:falseswipe",
    "tm:fling",
    "tm:flipturn",
    "tm:focusenergy",
    "tm:furycutter",
    "tm:grassknot",
    "tm:hail",
    "tm:helpinghand",
    "tm:hydropump",
    "tm:icebeam",
    "tm:icywind",
    "tm:irontail",
    "tm:knockoff",
    "tm:liquidation",
    "tm:protect",
    "tm:raindance",
    "tm:razorshell",
    "tm:rest",
    "tm:retaliate",
    "tm:revenge",
    "tm:rocksmash",
    "tm:screech",
    "tm:sleeptalk",
    "tm:snowscape",
    "tm:substitute",
    "tm:surf",
    "tm:swift",
    "tm:takedown",
    "tm:taunt",
    "tm:terablast",
    "tm:thief",
    "tm:vacuumwave",
    "tm:waterfall",
    "tm:waterpledge",
    "tm:waterpulse",
    "tm:whirlpool",
    "tm:workup",
    "tm:xscissor",
    "tutor:aerialace",
    "tutor:aquatail",
    "tutor:covet",
    "tutor:dive",
    "tutor:falseswipe",
    "tutor:flipturn",
    "tutor:focusenergy",
    "tutor:furycutter",
    "tutor:helpinghand",
    "tutor:icebeam",
    "tutor:icywind",
    "tutor:irontail",
    "tutor:knockoff",
    "tutor:liquidation",
    "tutor:rest",
    "tutor:rocksmash",
    "tutor:sleeptalk",
    "tutor:swift",
    "tutor:vacuumwave",
    "tutor:waterpledge",
    "tutor:waterpulse",
    "tutor:xscissor" ],
  "labels": [
    "gen9"
  ],
  "pokedex": [
    "He refused to evolve and chose a different path; his physical particularities and his resolve allowed him to train and fight alongside Urshifu. People call him Jetfoot because of his unique fighting style and how quick he is on his feet for a Dewott."
  ],
  "baseFriendship": 50,
  "evYield": {
    "hp": 0,
    "attack": 0,
    "defence": 0,
    "special_attack": 0,
    "special_defence": 0,
    "speed": 2
  },
  "height": 8,
  "weight": 245,
  "aspects": [],
  "cannotDynamax": false,
  "behaviour": {
    "moving": {
      "canLook": true,
      "walk": {
        "avoidsLand": false,
        "walkSpeed": 1
      },
      "swim": {
        "swimSpeed": 1,
        "canBreatheUnderwater": true,
        "canSwimInWater": true,
        "canSwimInLava": false
      }
    }
  }
}
